argiletum/devtools/__init__.py
argiletum/devtools/__version__.py
argiletum_devtools-1.0.0.dist-info/METADATA
argiletum_devtools-1.0.0.dist-info/WHEEL
argiletum_devtools-1.0.0.dist-info/licenses/LICENSE
argiletum_devtools-1.0.0.dist-info/RECORD
